{
  "scanned_at": "2026-04-26 00:07 UTC",
  "n_markets": 46552,
  "bargains": [],
  "movers": [
    {
      "type": "price_mover",
      "question": "Washington Nationals vs. Chicago White Sox: O/U 7.5",
      "slug": "mlb-wsh-cws-2026-04-25-total-7pt5",
      "prev_price": 0.1,
      "current_price": 0.9995,
      "move_pct": 89.95,
      "liquidity": 341072.86579,
      "volume": 28634.80732
    },
    {
      "type": "price_mover",
      "question": "Botafogo FR vs. SC Internacional: O/U 3.5",
      "slug": "bra-bot-int-2026-04-25-total-3pt5",
      "prev_price": 0.12,
      "current_price": 0.9995,
      "move_pct": 87.95,
      "liquidity": 71323.91928,
      "volume": 4043.227521000001
    },
    {
      "type": "price_mover",
      "question": "UFC Fight Night: Jafel Filho vs. Cody Durden (Flyweight, Prelims)",
      "slug": "ufc-jaf-cod2-2026-04-25",
      "prev_price": 0.835,
      "current_price": 0.0005,
      "move_pct": -83.45,
      "liquidity": 45559.01995,
      "volume": 375262.4842689999
    },
    {
      "type": "price_mover",
      "question": "Club ABB vs. Club Blooming: O/U 4.5",
      "slug": "bol1-abb-blo-2026-04-25-total-4pt5",
      "prev_price": 0.17,
      "current_price": 0.9995,
      "move_pct": 82.95,
      "liquidity": 5820.3563,
      "volume": 471.807243
    },
    {
      "type": "price_mover",
      "question": "Washington Nationals vs. Chicago White Sox: O/U 6.5",
      "slug": "mlb-wsh-cws-2026-04-25-total-6pt5",
      "prev_price": 0.19,
      "current_price": 0.9995,
      "move_pct": 80.95,
      "liquidity": 341877.54165,
      "volume": 12030.237030999999
    },
    {
      "type": "price_mover",
      "question": "Miami Marlins vs. San Francisco Giants: O/U 7.5",
      "slug": "mlb-mia-sf-2026-04-25-total-7pt5",
      "prev_price": 0.2,
      "current_price": 0.9995,
      "move_pct": 79.95,
      "liquidity": 330827.38612,
      "volume": 24516.964841000008
    },
    {
      "type": "price_mover",
      "question": "Minnesota United FC vs. Los Angeles FC: O/U 1.5",
      "slug": "mls-min-laf-2026-04-25-total-1pt5",
      "prev_price": 0.795,
      "current_price": 0.0005,
      "move_pct": -79.45,
      "liquidity": 36658.6286,
      "volume": 17710.13436
    },
    {
      "type": "price_mover",
      "question": "Exact Score: Minnesota United FC 0 - 1 Los Angeles FC?",
      "slug": "mls-min-laf-2026-04-25-exact-score-0-1",
      "prev_price": 0.215,
      "current_price": 0.9995,
      "move_pct": 78.45,
      "liquidity": 214020.24958,
      "volume": 5.58
    },
    {
      "type": "price_mover",
      "question": "Deportivo Pereira vs. Atlético Nacional: O/U 1.5",
      "slug": "col1-dep-atn-2026-04-25-total-1pt5",
      "prev_price": 0.78,
      "current_price": 0.0005,
      "move_pct": -77.95,
      "liquidity": 15267.83773,
      "volume": 894.0039050000001
    },
    {
      "type": "price_mover",
      "question": "Spread: San Francisco Giants (-1.5)",
      "slug": "mlb-mia-sf-2026-04-25-spread-home-1pt5",
      "prev_price": 0.23,
      "current_price": 0.9995,
      "move_pct": 76.95,
      "liquidity": 247944.25375,
      "volume": 4044.245321
    },
    {
      "type": "price_mover",
      "question": "Washington Nationals vs. Chicago White Sox: O/U 5.5",
      "slug": "mlb-wsh-cws-2026-04-25-total-5pt5",
      "prev_price": 0.245,
      "current_price": 0.9995,
      "move_pct": 75.45,
      "liquidity": 339872.62017,
      "volume": 14103.415636000003
    },
    {
      "type": "price_mover",
      "question": "UFC Fight Night: Eric McConico vs. Rodolfo Vieira (null, Prelims)",
      "slug": "ufc-eri15-rod1-2026-04-25",
      "prev_price": 0.245,
      "current_price": 0.996,
      "move_pct": 75.1,
      "liquidity": 82857.61196,
      "volume": 198340.45050099978
    },
    {
      "type": "price_mover",
      "question": "Spread: Washington Nationals (-2.5)",
      "slug": "mlb-wsh-cws-2026-04-25-spread-away-2pt5",
      "prev_price": 0.27,
      "current_price": 0.9995,
      "move_pct": 72.95,
      "liquidity": 229815.97205,
      "volume": 161.798831
    },
    {
      "type": "price_mover",
      "question": "Will EC Bahia vs. Santos FC end in a draw?",
      "slug": "bra-bah-san-2026-04-25-draw",
      "prev_price": 0.29,
      "current_price": 0.9995,
      "move_pct": 70.95,
      "liquidity": 260521.59961,
      "volume": 19735.074047
    },
    {
      "type": "price_mover",
      "question": "Cleveland Guardians vs. Toronto Blue Jays: O/U 7.5",
      "slug": "mlb-cle-tor-2026-04-25-total-7pt5",
      "prev_price": 0.29,
      "current_price": 0.9995,
      "move_pct": 70.95,
      "liquidity": 256010.71971,
      "volume": 42294.499293
    },
    {
      "type": "price_mover",
      "question": "Botafogo FR vs. SC Internacional: O/U 2.5",
      "slug": "bra-bot-int-2026-04-25-total-2pt5",
      "prev_price": 0.3,
      "current_price": 0.9995,
      "move_pct": 69.95,
      "liquidity": 111521.69192,
      "volume": 31027.526177000007
    },
    {
      "type": "price_mover",
      "question": "Club ABB vs. Club Blooming: O/U 3.5",
      "slug": "bol1-abb-blo-2026-04-25-total-3pt5",
      "prev_price": 0.31,
      "current_price": 0.9995,
      "move_pct": 68.95,
      "liquidity": 7958.54802,
      "volume": 149.66
    },
    {
      "type": "price_mover",
      "question": "Will there be a run scored in the first inning?: San Diego Padres vs. Arizona Diamondbacks",
      "slug": "mlb-sd-ari-2026-04-25-nrfi",
      "prev_price": 0.69,
      "current_price": 0.0005,
      "move_pct": -68.95,
      "liquidity": 235944.3878,
      "volume": 5011.671430000001
    },
    {
      "type": "price_mover",
      "question": "Will Pumas de la UNAM win on 2026-04-25?",
      "slug": "mex-pac-pum-2026-04-25-pum",
      "prev_price": 0.265,
      "current_price": 0.935,
      "move_pct": 67.0,
      "liquidity": 9371.6415,
      "volume": 35200.403706000005
    },
    {
      "type": "price_mover",
      "question": "Will Botafogo FR vs. SC Internacional end in a draw?",
      "slug": "bra-bot-int-2026-04-25-draw",
      "prev_price": 0.335,
      "current_price": 0.9995,
      "move_pct": 66.45,
      "liquidity": 247956.54172,
      "volume": 19253.54852
    },
    {
      "type": "price_mover",
      "question": "CD Comerciantes Unidos vs. CS Cristal: O/U 1.5",
      "slug": "per1-ccu-csc-2026-04-25-total-1pt5",
      "prev_price": 0.64,
      "current_price": 0.0005,
      "move_pct": -63.95,
      "liquidity": 9792.80884,
      "volume": 199.139544
    },
    {
      "type": "price_mover",
      "question": "Miami Marlins vs. San Francisco Giants: O/U 5.5",
      "slug": "mlb-mia-sf-2026-04-25-total-5pt5",
      "prev_price": 0.365,
      "current_price": 0.9995,
      "move_pct": 63.45,
      "liquidity": 225666.69494,
      "volume": 830.889997
    },
    {
      "type": "price_mover",
      "question": "Will Cruzeiro EC win on 2026-04-25?",
      "slug": "bra-cre-cru-2026-04-25-cru",
      "prev_price": 0.37,
      "current_price": 0.9995,
      "move_pct": 62.95,
      "liquidity": 287083.33261,
      "volume": 55606.527213
    },
    {
      "type": "price_mover",
      "question": "EC Bahia vs. Santos FC: O/U 3.5",
      "slug": "bra-bah-san-2026-04-25-total-3pt5",
      "prev_price": 0.37,
      "current_price": 0.9995,
      "move_pct": 62.95,
      "liquidity": 50612.60307,
      "volume": 7556.433625999997
    },
    {
      "type": "price_mover",
      "question": "Minnesota United FC vs. Los Angeles FC: Both Teams to Score",
      "slug": "mls-min-laf-2026-04-25-btts",
      "prev_price": 0.61,
      "current_price": 0.0005,
      "move_pct": -60.95,
      "liquidity": 23254.25255,
      "volume": 652.657355
    },
    {
      "type": "price_mover",
      "question": "Botafogo FR vs. SC Internacional: Both Teams to Score",
      "slug": "bra-bot-int-2026-04-25-btts",
      "prev_price": 0.395,
      "current_price": 0.9995,
      "move_pct": 60.45,
      "liquidity": 61302.06765,
      "volume": 5598.6353789999985
    },
    {
      "type": "price_mover",
      "question": "Valorant: NRG vs 100 Thieves - Map 1 Winner",
      "slug": "val-nrg-100t1-2026-04-25-game1",
      "prev_price": 0.605,
      "current_price": 0.0005,
      "move_pct": -60.45,
      "liquidity": 178333.68242,
      "volume": 79605.26511999997
    },
    {
      "type": "price_mover",
      "question": "Deportivo Pereira vs. Atlético Nacional: Both Teams to Score",
      "slug": "col1-dep-atn-2026-04-25-btts",
      "prev_price": 0.575,
      "current_price": 0.0005,
      "move_pct": -57.45,
      "liquidity": 15581.23535,
      "volume": 501.23747499999985
    },
    {
      "type": "price_mover",
      "question": "Bitcoin Up or Down - April 25, 6PM ET",
      "slug": "bitcoin-up-or-down-april-25-2026-6pm-et",
      "prev_price": 0.435,
      "current_price": 0.9995,
      "move_pct": 56.45,
      "liquidity": 524717.56256,
      "volume": 71050.17298699997
    },
    {
      "type": "price_mover",
      "question": "Will CA Sarmiento win on 2026-04-25?",
      "slug": "arg-cas-tig-2026-04-25-cas",
      "prev_price": 0.245,
      "current_price": 0.805,
      "move_pct": 56.0,
      "liquidity": 6125.2604,
      "volume": 13514.347159000008
    }
  ],
  "longshots": [
    {
      "type": "longshot",
      "question": "Will the Edmonton Oilers win the 2026 NHL Stanley Cup?",
      "slug": "will-the-edmonton-oilers-win-the-2026-nhl-stanley-cup",
      "longshot_price": 0.055,
      "favorite_price": 0.945,
      "hours_to_close": 1559.9,
      "volume": 719822.0842500046
    },
    {
      "type": "longshot",
      "question": "Will the Dallas Stars win the 2026 NHL Stanley Cup?",
      "slug": "will-the-dallas-stars-win-the-2026-nhl-stanley-cup",
      "longshot_price": 0.08,
      "favorite_price": 0.92,
      "hours_to_close": 1559.9,
      "volume": 1423751.8341479916
    },
    {
      "type": "longshot",
      "question": "Will the Vegas Golden Knights win the 2026 NHL Stanley Cup?",
      "slug": "will-the-vegas-golden-knights-win-the-2026-nhl-stanley-cup",
      "longshot_price": 0.0415,
      "favorite_price": 0.9585,
      "hours_to_close": 1559.9,
      "volume": 1661085.8835719922
    },
    {
      "type": "longshot",
      "question": "Will the Tampa Bay Lightning win the 2026 NHL Stanley Cup?",
      "slug": "will-the-tampa-bay-lightning-win-the-2026-nhl-stanley-cup",
      "longshot_price": 0.0635,
      "favorite_price": 0.9365,
      "hours_to_close": 1559.9,
      "volume": 1826404.5405779704
    },
    {
      "type": "longshot",
      "question": "Will the Minnesota Wild win the 2026 NHL Stanley Cup?",
      "slug": "will-the-minnesota-wild-win-the-2026-nhl-stanley-cup",
      "longshot_price": 0.0245,
      "favorite_price": 0.9755,
      "hours_to_close": 1559.9,
      "volume": 8906309.974852927
    },
    {
      "type": "longshot",
      "question": "Will the Utah Mammoth win the 2026 NHL Stanley Cup?",
      "slug": "will-the-utah-mammoth-win-the-2026-nhl-stanley-cup",
      "longshot_price": 0.0365,
      "favorite_price": 0.9635,
      "hours_to_close": 1559.9,
      "volume": 1211467.4682039947
    },
    {
      "type": "longshot",
      "question": "Will the Philadelphia Flyers win the 2026 NHL Stanley Cup?",
      "slug": "will-the-philadelphia-flyers-win-the-2026-nhl-stanley-cup",
      "longshot_price": 0.0405,
      "favorite_price": 0.9595,
      "hours_to_close": 1559.9,
      "volume": 1310850.6278780021
    },
    {
      "type": "longshot",
      "question": "Will the Anaheim Ducks win the 2026 NHL Stanley Cup?",
      "slug": "will-the-anaheim-ducks-win-the-2026-nhl-stanley-cup",
      "longshot_price": 0.0305,
      "favorite_price": 0.9695,
      "hours_to_close": 1559.9,
      "volume": 1123772.1483389991
    },
    {
      "type": "longshot",
      "question": "Will the Montreal Canadiens win the 2026 NHL Stanley Cup?",
      "slug": "will-the-montreal-canadiens-win-the-2026-nhl-stanley-cup",
      "longshot_price": 0.0635,
      "favorite_price": 0.9365,
      "hours_to_close": 1559.9,
      "volume": 1805915.1080339896
    },
    {
      "type": "longshot",
      "question": "Will the Boston Bruins win the 2026 NHL Stanley Cup?",
      "slug": "will-the-boston-bruins-win-the-2026-nhl-stanley-cup",
      "longshot_price": 0.0115,
      "favorite_price": 0.9885,
      "hours_to_close": 1559.9,
      "volume": 1372368.418402997
    },
    {
      "type": "longshot",
      "question": "Will the Buffalo Sabres win the 2026 NHL Stanley Cup?",
      "slug": "will-the-buffalo-sabres-win-the-2026-nhl-stanley-cup",
      "longshot_price": 0.0635,
      "favorite_price": 0.9365,
      "hours_to_close": 1559.9,
      "volume": 3208651.716858983
    },
    {
      "type": "longshot",
      "question": "Will the Cleveland Cavaliers win the 2026 NBA Finals?",
      "slug": "will-the-cleveland-cavaliers-win-the-2026-nba-finals",
      "longshot_price": 0.0465,
      "favorite_price": 0.9535,
      "hours_to_close": 1583.9,
      "volume": 9889407.37986497
    },
    {
      "type": "longshot",
      "question": "Will the New York Knicks win the 2026 NBA Finals?",
      "slug": "will-the-new-york-knicks-win-the-2026-nba-finals",
      "longshot_price": 0.0255,
      "favorite_price": 0.9745,
      "hours_to_close": 1583.9,
      "volume": 8721814.451077737
    },
    {
      "type": "longshot",
      "question": "Will the Minnesota Timberwolves win the 2026 NBA Finals?",
      "slug": "will-the-minnesota-timberwolves-win-the-2026-nba-finals",
      "longshot_price": 0.0315,
      "favorite_price": 0.9685,
      "hours_to_close": 1583.9,
      "volume": 10649465.806324875
    },
    {
      "type": "longshot",
      "question": "Will the Los Angeles Lakers win the 2026 NBA Finals?",
      "slug": "will-the-los-angeles-lakers-win-the-2026-nba-finals",
      "longshot_price": 0.039,
      "favorite_price": 0.961,
      "hours_to_close": 1583.9,
      "volume": 16315808.002212042
    },
    {
      "type": "longshot",
      "question": "Will the Denver Nuggets win the 2026 NBA Finals?",
      "slug": "will-the-denver-nuggets-win-the-2026-nba-finals",
      "longshot_price": 0.065,
      "favorite_price": 0.935,
      "hours_to_close": 1583.9,
      "volume": 6409822.575705001
    },
    {
      "type": "longshot",
      "question": "Will the Detroit Pistons win the 2026 NBA Finals?",
      "slug": "will-the-detroit-pistons-win-the-2026-nba-finals",
      "longshot_price": 0.0215,
      "favorite_price": 0.9785,
      "hours_to_close": 1583.9,
      "volume": 11769947.602751702
    },
    {
      "type": "longshot",
      "question": "MegaETH market cap (FDV) >$6B one day after launch?",
      "slug": "megaeth-market-cap-fdv-6b-one-day-after-launch-365-559-334-815-776-488-224-766",
      "longshot_price": 0.0155,
      "favorite_price": 0.9845,
      "hours_to_close": 1559.9,
      "volume": 2591857.995655021
    },
    {
      "type": "longshot",
      "question": "Will Germany win the 2026 FIFA World Cup?",
      "slug": "will-germany-win-the-2026-fifa-world-cup-467",
      "longshot_price": 0.0525,
      "favorite_price": 0.9475,
      "hours_to_close": 2039.9,
      "volume": 13551903.826245725
    },
    {
      "type": "longshot",
      "question": "Will Portugal win the 2026 FIFA World Cup?",
      "slug": "will-portugal-win-the-2026-fifa-world-cup-912",
      "longshot_price": 0.078,
      "favorite_price": 0.922,
      "hours_to_close": 2039.9,
      "volume": 15635571.447377615
    },
    {
      "type": "longshot",
      "question": "Will Netherlands win the 2026 FIFA World Cup?",
      "slug": "will-netherlands-win-the-2026-fifa-world-cup-739",
      "longshot_price": 0.0335,
      "favorite_price": 0.9665,
      "hours_to_close": 2039.9,
      "volume": 15252316.782477899
    },
    {
      "type": "longshot",
      "question": "Will USA win the 2026 FIFA World Cup?",
      "slug": "will-usa-win-the-2026-fifa-world-cup-467",
      "longshot_price": 0.0125,
      "favorite_price": 0.9875,
      "hours_to_close": 2039.9,
      "volume": 23279272.89542294
    },
    {
      "type": "longshot",
      "question": "Will Uruguay win the 2026 FIFA World Cup?",
      "slug": "will-uruguay-win-the-2026-fifa-world-cup-932",
      "longshot_price": 0.0105,
      "favorite_price": 0.9895,
      "hours_to_close": 2039.9,
      "volume": 14208584.483403988
    },
    {
      "type": "longshot",
      "question": "Will Mexico win the 2026 FIFA World Cup?",
      "slug": "will-mexico-win-the-2026-fifa-world-cup-529",
      "longshot_price": 0.0105,
      "favorite_price": 0.9895,
      "hours_to_close": 2039.9,
      "volume": 15465259.10928031
    },
    {
      "type": "longshot",
      "question": "Will Belgium win the 2026 FIFA World Cup?",
      "slug": "will-belgium-win-the-2026-fifa-world-cup-358",
      "longshot_price": 0.0205,
      "favorite_price": 0.9795,
      "hours_to_close": 2039.9,
      "volume": 14233629.30386807
    },
    {
      "type": "longshot",
      "question": "Will Colombia win the 2026 FIFA World Cup?",
      "slug": "will-colombia-win-the-2026-fifa-world-cup-734",
      "longshot_price": 0.0165,
      "favorite_price": 0.9835,
      "hours_to_close": 2039.9,
      "volume": 13122879.808426775
    },
    {
      "type": "longshot",
      "question": "Will Japan win the 2026 FIFA World Cup?",
      "slug": "will-japan-win-the-2026-fifa-world-cup-112",
      "longshot_price": 0.0215,
      "favorite_price": 0.9785,
      "hours_to_close": 2039.9,
      "volume": 17160353.331260018
    },
    {
      "type": "longshot",
      "question": "Will Norway win the 2026 FIFA World Cup?",
      "slug": "will-norway-win-the-2026-fifa-world-cup-893",
      "longshot_price": 0.0225,
      "favorite_price": 0.9775,
      "hours_to_close": 2039.9,
      "volume": 13419352.399840316
    },
    {
      "type": "longshot",
      "question": "Will Morocco win the 2026 FIFA World Cup?",
      "slug": "will-morocco-win-the-2026-fifa-world-cup-464",
      "longshot_price": 0.0165,
      "favorite_price": 0.9835,
      "hours_to_close": 2039.9,
      "volume": 15418418.03489915
    },
    {
      "type": "longshot",
      "question": "Will Pete Buttigieg win the 2028 Democratic presidential nomination?",
      "slug": "will-pete-buttigieg-win-the-2028-democratic-presidential-nomination-687",
      "longshot_price": 0.041,
      "favorite_price": 0.959,
      "hours_to_close": 22223.9,
      "volume": 10289478.73005163
    },
    {
      "type": "longshot",
      "question": "Will Josh Shapiro win the 2028 Democratic presidential nomination?",
      "slug": "will-josh-shapiro-win-the-2028-democratic-presidential-nomination-977",
      "longshot_price": 0.0365,
      "favorite_price": 0.9635,
      "hours_to_close": 22223.9,
      "volume": 7330039.57416926
    },
    {
      "type": "longshot",
      "question": "Will Wes Moore win the 2028 Democratic presidential nomination?",
      "slug": "will-wes-moore-win-the-2028-democratic-presidential-nomination-714",
      "longshot_price": 0.0115,
      "favorite_price": 0.9885,
      "hours_to_close": 22223.9,
      "volume": 15209858.81764197
    },
    {
      "type": "longshot",
      "question": "Will Kamala Harris win the 2028 Democratic presidential nomination?",
      "slug": "will-kamala-harris-win-the-2028-democratic-presidential-nomination-641",
      "longshot_price": 0.0755,
      "favorite_price": 0.9245,
      "hours_to_close": 22223.9,
      "volume": 11223680.943448003
    },
    {
      "type": "longshot",
      "question": "Will Gretchen Whitmer win the 2028 Democratic presidential nomination?",
      "slug": "will-gretchen-whitmer-win-the-2028-democratic-presidential-nomination-676",
      "longshot_price": 0.0125,
      "favorite_price": 0.9875,
      "hours_to_close": 22223.9,
      "volume": 8453676.17830103
    },
    {
      "type": "longshot",
      "question": "Will Andy Beshear win the 2028 Democratic presidential nomination?",
      "slug": "will-andy-beshear-win-the-2028-democratic-presidential-nomination-832",
      "longshot_price": 0.0215,
      "favorite_price": 0.9785,
      "hours_to_close": 22223.9,
      "volume": 11557805.377857868
    },
    {
      "type": "longshot",
      "question": "Will Jon Ossoff win the 2028 Democratic presidential nomination?",
      "slug": "will-jon-ossoff-win-the-2028-democratic-presidential-nomination-885",
      "longshot_price": 0.0545,
      "favorite_price": 0.9455,
      "hours_to_close": 22223.9,
      "volume": 10113946.102253936
    },
    {
      "type": "longshot",
      "question": "Will J.B. Pritzker win the 2028 Democratic presidential nomination?",
      "slug": "will-jb-pritzker-win-the-2028-democratic-presidential-nomination-288",
      "longshot_price": 0.0195,
      "favorite_price": 0.9805,
      "hours_to_close": 22223.9,
      "volume": 13639249.99247704
    },
    {
      "type": "longshot",
      "question": "Will Mark Kelly win the 2028 Democratic presidential nomination?",
      "slug": "will-mark-kelly-win-the-2028-democratic-presidential-nomination-479",
      "longshot_price": 0.0255,
      "favorite_price": 0.9745,
      "hours_to_close": 22223.9,
      "volume": 14836501.849914543
    },
    {
      "type": "longshot",
      "question": "Will Rahm Emanuel win the 2028 Democratic presidential nomination?",
      "slug": "will-rahm-emanuel-win-the-2028-democratic-presidential-nomination-299",
      "longshot_price": 0.0195,
      "favorite_price": 0.9805,
      "hours_to_close": 22223.9,
      "volume": 13091753.838844001
    },
    {
      "type": "longshot",
      "question": "Will Roy Cooper win the 2028 Democratic presidential nomination?",
      "slug": "will-roy-cooper-win-the-2028-democratic-presidential-nomination-286",
      "longshot_price": 0.0115,
      "favorite_price": 0.9885,
      "hours_to_close": 22223.9,
      "volume": 28381248.531037107
    },
    {
      "type": "longshot",
      "question": "Will John Fetterman win the 2028 Democratic presidential nomination?",
      "slug": "will-john-fetterman-win-the-2028-democratic-presidential-nomination-941",
      "longshot_price": 0.0105,
      "favorite_price": 0.9895,
      "hours_to_close": 22223.9,
      "volume": 18500658.86242225
    },
    {
      "type": "longshot",
      "question": "Will Jon Stewart win the 2028 Democratic presidential nomination?",
      "slug": "will-jon-stewart-win-the-2028-democratic-presidential-nomination-518",
      "longshot_price": 0.0215,
      "favorite_price": 0.9785,
      "hours_to_close": 22223.9,
      "volume": 22433563.62657607
    },
    {
      "type": "longshot",
      "question": "Will Dwayne 'The Rock' Johnson win the 2028 Democratic presidential nomination?",
      "slug": "will-dwayne-the-rock-johnson-win-the-2028-democratic-presidential-nomination",
      "longshot_price": 0.0115,
      "favorite_price": 0.9885,
      "hours_to_close": 22223.9,
      "volume": 11105931.231510047
    },
    {
      "type": "longshot",
      "question": "Will Ro Khanna win the 2028 Democratic presidential nomination?",
      "slug": "will-ro-khanna-win-the-2028-democratic-presidential-nomination",
      "longshot_price": 0.0185,
      "favorite_price": 0.9815,
      "hours_to_close": 22223.9,
      "volume": 9766500.222689327
    },
    {
      "type": "longshot",
      "question": "Will James Talarico win the 2028 Democratic presidential nomination?",
      "slug": "will-james-talarico-win-the-2028-democratic-presidential-nomination",
      "longshot_price": 0.0205,
      "favorite_price": 0.9795,
      "hours_to_close": 22223.9,
      "volume": 8845874.60443105
    },
    {
      "type": "longshot",
      "question": "Will Alexandria Ocasio-Cortez win the 2028 US Presidential Election?",
      "slug": "will-alexandria-ocasio-cortez-win-the-2028-us-presidential-election",
      "longshot_price": 0.0605,
      "favorite_price": 0.9395,
      "hours_to_close": 22223.9,
      "volume": 11198367.309181811
    },
    {
      "type": "longshot",
      "question": "Will Pete Buttigieg win the 2028 US Presidential Election?",
      "slug": "will-pete-buttigieg-win-the-2028-us-presidential-election",
      "longshot_price": 0.0195,
      "favorite_price": 0.9805,
      "hours_to_close": 22223.9,
      "volume": 4148601.7809499674
    },
    {
      "type": "longshot",
      "question": "Will Josh Shapiro win the 2028 US Presidential Election?",
      "slug": "will-josh-shapiro-win-the-2028-us-presidential-election",
      "longshot_price": 0.021,
      "favorite_price": 0.979,
      "hours_to_close": 22223.9,
      "volume": 6060486.66162091
    },
    {
      "type": "longshot",
      "question": "Will Andy Beshear win the 2028 US Presidential Election?",
      "slug": "will-andy-beshear-win-the-2028-us-presidential-election",
      "longshot_price": 0.0135,
      "favorite_price": 0.9865,
      "hours_to_close": 22223.9,
      "volume": 17856838.39348811
    },
    {
      "type": "longshot",
      "question": "Will Kamala Harris win the 2028 US Presidential Election?",
      "slug": "will-kamala-harris-win-the-2028-us-presidential-election",
      "longshot_price": 0.0425,
      "favorite_price": 0.9575,
      "hours_to_close": 22223.9,
      "volume": 7168908.296848005
    }
  ]
}